LICENSE
MANIFEST.in
README.rst
setup.cfg
setup.py
versioneer.py
tests/__init__.py
tests/test_folder.py
tests/test_general.py
tpDcc/__init__.py
tpDcc/libs/__init__.py
tpDcc/libs/python/__init__.py
tpDcc/libs/python/__logging__.ini
tpDcc/libs/python/__version__.py
tpDcc/libs/python/_version.py
tpDcc/libs/python/attributes.py
tpDcc/libs/python/code.py
tpDcc/libs/python/color.py
tpDcc/libs/python/contexts.py
tpDcc/libs/python/dcc.py
tpDcc/libs/python/debug.py
tpDcc/libs/python/decorators.py
tpDcc/libs/python/download.py
tpDcc/libs/python/email.py
tpDcc/libs/python/enum.py
tpDcc/libs/python/fileio.py
tpDcc/libs/python/folder.py
tpDcc/libs/python/importer.py
tpDcc/libs/python/jsonio.py
tpDcc/libs/python/language.py
tpDcc/libs/python/log.py
tpDcc/libs/python/modules.py
tpDcc/libs/python/name.py
tpDcc/libs/python/observable.py
tpDcc/libs/python/osplatform.py
tpDcc/libs/python/path.py
tpDcc/libs/python/preferences.py
tpDcc/libs/python/process.py
tpDcc/libs/python/profiler.py
tpDcc/libs/python/python.py
tpDcc/libs/python/reloader.py
tpDcc/libs/python/security.py
tpDcc/libs/python/settings.py
tpDcc/libs/python/signal.py
tpDcc/libs/python/sort.py
tpDcc/libs/python/sqlite.py
tpDcc/libs/python/strings.py
tpDcc/libs/python/timedate.py
tpDcc/libs/python/timers.py
tpDcc/libs/python/version.py
tpDcc/libs/python/web.py
tpDcc/libs/python/win32.py
tpDcc/libs/python/yamlio.py
tpDcc/libs/python/yamlordereddictloader.py
tpDcc_libs_python.egg-info/PKG-INFO
tpDcc_libs_python.egg-info/SOURCES.txt
tpDcc_libs_python.egg-info/dependency_links.txt
tpDcc_libs_python.egg-info/not-zip-safe
tpDcc_libs_python.egg-info/requires.txt
tpDcc_libs_python.egg-info/top_level.txt