Metadata-Version: 2.1
Name: tpDcc-libs-python
Version: 0.0.15
Summary: Collection of Python utilities modules to work with Python and DCCs
Home-page: https://github.com/tpDcc/tpDcc-libs-python
Author: Tomas Poveda
Author-email: tpovedatd@gmail.com
License: MIT
Platform: UNKNOWN
Provides-Extra: dev
Provides-Extra: test
